{
  "layer_1": {
    "experiment_name": "hsv_colour_one_red",
    "model_config": "Gemma-2-9B",
    "display_labels": [
      "Red",
      "Yellow",
      "Green",
      "Cyan",
      "Blue",
      "Magenta"
    ],
    "states_pca": [
      [
        -1.3320865631103516,
        0.0014858245849609375
      ],
      [
        -0.3080329895019531,
        -0.008334636688232422
      ],
      [
        0.32475852966308594,
        0.14719533920288086
      ],
      [
        0.5098590850830078,
        0.08591270446777344
      ],
      [
        0.3990669250488281,
        0.032067298889160156
      ],
      [
        0.40643310546875,
        -0.25832033157348633
      ]
    ],
    "explained_variance": [
      0.9233189821243286,
      0.03495147079229355,
      0.022499658167362213,
      0.015217949636280537,
      0.004012005403637886
    ]
  },
  "layer_10": {
    "experiment_name": "hsv_colour_one_red",
    "model_config": "Gemma-2-9B",
    "display_labels": [
      "Red",
      "Yellow",
      "Green",
      "Cyan",
      "Blue",
      "Magenta"
    ],
    "states_pca": [
      [
        -19.3029842376709,
        -0.8221607208251953
      ],
      [
        1.004842758178711,
        4.987968444824219
      ],
      [
        4.5988006591796875,
        2.9075002670288086
      ],
      [
        3.910055160522461,
        0.7370767593383789
      ],
      [
        6.423151016235352,
        -3.5474958419799805
      ],
      [
        3.366128921508789,
        -4.262882232666016
      ]
    ],
    "explained_variance": [
      0.7342503070831299,
      0.10365182161331177,
      0.08291241526603699,
      0.05218544602394104,
      0.026999907568097115
    ]
  },
  "layer_11": {
    "experiment_name": "hsv_colour_one_red",
    "model_config": "Gemma-2-9B",
    "display_labels": [
      "Red",
      "Yellow",
      "Green",
      "Cyan",
      "Blue",
      "Magenta"
    ],
    "states_pca": [
      [
        -22.627094268798828,
        -0.9730167388916016
      ],
      [
        0.7445154190063477,
        5.287036895751953
      ],
      [
        5.466462135314941,
        3.9457740783691406
      ],
      [
        4.934020042419434,
        0.7435569763183594
      ],
      [
        7.479691505432129,
        -4.358569145202637
      ],
      [
        4.002406120300293,
        -4.644791603088379
      ]
    ],
    "explained_variance": [
      0.7495672702789307,
      0.10044518858194351,
      0.07608900964260101,
      0.05146031826734543,
      0.022438105195760727
    ]
  },
  "layer_12": {
    "experiment_name": "hsv_colour_one_red",
    "model_config": "Gemma-2-9B",
    "display_labels": [
      "Red",
      "Yellow",
      "Green",
      "Cyan",
      "Blue",
      "Magenta"
    ],
    "states_pca": [
      [
        -25.681554794311523,
        1.7365245819091797
      ],
      [
        0.058943748474121094,
        -6.959692001342773
      ],
      [
        6.466861724853516,
        -4.828313827514648
      ],
      [
        5.868830680847168,
        -0.05960273742675781
      ],
      [
        9.207405090332031,
        6.890255928039551
      ],
      [
        4.079512596130371,
        3.2208499908447266
      ]
    ],
    "explained_variance": [
      0.7217849493026733,
      0.11433213204145432,
      0.08417631685733795,
      0.05768612027168274,
      0.022020520642399788
    ]
  },
  "layer_13": {
    "experiment_name": "hsv_colour_one_red",
    "model_config": "Gemma-2-9B",
    "display_labels": [
      "Red",
      "Yellow",
      "Green",
      "Cyan",
      "Blue",
      "Magenta"
    ],
    "states_pca": [
      [
        -28.461776733398438,
        2.2589569091796875
      ],
      [
        -0.7361288070678711,
        -8.786357879638672
      ],
      [
        7.832302093505859,
        -5.278432846069336
      ],
      [
        7.035820007324219,
        -0.07583808898925781
      ],
      [
        10.278464317321777,
        8.280763626098633
      ],
      [
        4.051321029663086,
        3.600907325744629
      ]
    ],
    "explained_variance": [
      0.7082331776618958,
      0.13011157512664795,
      0.08259395509958267,
      0.05904781445860863,
      0.020013457164168358
    ]
  },
  "layer_14": {
    "experiment_name": "hsv_colour_one_red",
    "model_config": "Gemma-2-9B",
    "display_labels": [
      "Red",
      "Yellow",
      "Green",
      "Cyan",
      "Blue",
      "Magenta"
    ],
    "states_pca": [
      [
        -30.223064422607422,
        2.3741540908813477
      ],
      [
        -1.4645071029663086,
        -9.750232696533203
      ],
      [
        9.050432205200195,
        -6.005287170410156
      ],
      [
        8.29101848602295,
        0.05973625183105469
      ],
      [
        10.4696044921875,
        9.053211212158203
      ],
      [
        3.876521110534668,
        4.268407344818115
      ]
    ],
    "explained_variance": [
      0.7007452845573425,
      0.13942916691303253,
      0.0850081667304039,
      0.05530555918812752,
      0.019511766731739044
    ]
  },
  "layer_15": {
    "experiment_name": "hsv_colour_one_red",
    "model_config": "Gemma-2-9B",
    "display_labels": [
      "Red",
      "Yellow",
      "Green",
      "Cyan",
      "Blue",
      "Magenta"
    ],
    "states_pca": [
      [
        -32.72515869140625,
        2.008098602294922
      ],
      [
        -1.9991626739501953,
        -10.269036293029785
      ],
      [
        10.688631057739258,
        -8.754124641418457
      ],
      [
        9.502214431762695,
        -0.20948410034179688
      ],
      [
        11.028514862060547,
        10.68301773071289
      ],
      [
        3.505035400390625,
        6.54151725769043
      ]
    ],
    "explained_variance": [
      0.6729632616043091,
      0.1633538454771042,
      0.08505839854478836,
      0.06158130615949631,
      0.017043177038431168
    ]
  },
  "layer_16": {
    "experiment_name": "hsv_colour_one_red",
    "model_config": "Gemma-2-9B",
    "display_labels": [
      "Red",
      "Yellow",
      "Green",
      "Cyan",
      "Blue",
      "Magenta"
    ],
    "states_pca": [
      [
        -36.17845916748047,
        -1.0091214179992676
      ],
      [
        -1.7681360244750977,
        10.254720687866211
      ],
      [
        12.768792152404785,
        10.664804458618164
      ],
      [
        10.725688934326172,
        0.2876729965209961
      ],
      [
        10.230249404907227,
        -12.044075012207031
      ],
      [
        4.221851825714111,
        -8.1539945602417
      ]
    ],
    "explained_variance": [
      0.6609898209571838,
      0.16656093299388885,
      0.08428515493869781,
      0.06907723844051361,
      0.01908695511519909
    ]
  },
  "layer_17": {
    "experiment_name": "hsv_colour_one_red",
    "model_config": "Gemma-2-9B",
    "display_labels": [
      "Red",
      "Yellow",
      "Green",
      "Cyan",
      "Blue",
      "Magenta"
    ],
    "states_pca": [
      [
        -43.47172927856445,
        1.5328140258789062
      ],
      [
        -2.3029394149780273,
        -11.826961517333984
      ],
      [
        14.26966381072998,
        -13.799385070800781
      ],
      [
        13.381135940551758,
        -0.08072090148925781
      ],
      [
        12.587976455688477,
        14.685527801513672
      ],
      [
        5.535887718200684,
        9.488771438598633
      ]
    ],
    "explained_variance": [
      0.6647947430610657,
      0.17203010618686676,
      0.0812729001045227,
      0.06367077678442001,
      0.018231432884931564
    ]
  },
  "layer_18": {
    "experiment_name": "hsv_colour_one_red",
    "model_config": "Gemma-2-9B",
    "display_labels": [
      "Red",
      "Yellow",
      "Green",
      "Cyan",
      "Blue",
      "Magenta"
    ],
    "states_pca": [
      [
        -42.3614616394043,
        0.06517171859741211
      ],
      [
        -2.746959686279297,
        10.167007446289062
      ],
      [
        15.734840393066406,
        14.382675170898438
      ],
      [
        14.259864807128906,
        0.4006361961364746
      ],
      [
        10.289794921875,
        -14.757108688354492
      ],
      [
        4.823886871337891,
        -10.258384704589844
      ]
    ],
    "explained_variance": [
      0.6566277742385864,
      0.1745961457490921,
      0.08179435133934021,
      0.06688479334115982,
      0.020097006112337112
    ]
  },
  "layer_19": {
    "experiment_name": "hsv_colour_one_red",
    "model_config": "Gemma-2-9B",
    "display_labels": [
      "Red",
      "Yellow",
      "Green",
      "Cyan",
      "Blue",
      "Magenta"
    ],
    "states_pca": [
      [
        -42.77101135253906,
        1.9397468566894531
      ],
      [
        -2.300943374633789,
        9.544962882995605
      ],
      [
        17.961706161499023,
        15.365002632141113
      ],
      [
        14.785296440124512,
        0.28312206268310547
      ],
      [
        8.334915161132812,
        -15.415679931640625
      ],
      [
        3.9900550842285156,
        -11.717144012451172
      ]
    ],
    "explained_variance": [
      0.6380813717842102,
      0.1830209344625473,
      0.0913480743765831,
      0.0670682042837143,
      0.02048145793378353
    ]
  },
  "layer_2": {
    "experiment_name": "hsv_colour_one_red",
    "model_config": "Gemma-2-9B",
    "display_labels": [
      "Red",
      "Yellow",
      "Green",
      "Cyan",
      "Blue",
      "Magenta"
    ],
    "states_pca": [
      [
        -1.9463162422180176,
        -0.21373581886291504
      ],
      [
        -0.21331000328063965,
        -0.07331562042236328
      ],
      [
        0.4270704984664917,
        0.26300930976867676
      ],
      [
        0.9338101148605347,
        -1.0073156356811523
      ],
      [
        0.49269914627075195,
        0.43416285514831543
      ],
      [
        0.3060450553894043,
        0.5971972942352295
      ]
    ],
    "explained_variance": [
      0.631136417388916,
      0.20295864343643188,
      0.11001083999872208,
      0.03627831116318703,
      0.019615737721323967
    ]
  },
  "layer_20": {
    "experiment_name": "hsv_colour_one_red",
    "model_config": "Gemma-2-9B",
    "display_labels": [
      "Red",
      "Yellow",
      "Green",
      "Cyan",
      "Blue",
      "Magenta"
    ],
    "states_pca": [
      [
        -43.45310974121094,
        3.0655746459960938
      ],
      [
        -2.2220687866210938,
        7.773155212402344
      ],
      [
        19.032604217529297,
        16.230941772460938
      ],
      [
        15.261981964111328,
        0.5916175842285156
      ],
      [
        7.838657379150391,
        -16.17278289794922
      ],
      [
        3.5419578552246094,
        -11.488574981689453
      ]
    ],
    "explained_variance": [
      0.6430959701538086,
      0.18250757455825806,
      0.09226991981267929,
      0.06133858487010002,
      0.020787840709090233
    ]
  },
  "layer_21": {
    "experiment_name": "hsv_colour_one_red",
    "model_config": "Gemma-2-9B",
    "display_labels": [
      "Red",
      "Yellow",
      "Green",
      "Cyan",
      "Blue",
      "Magenta"
    ],
    "states_pca": [
      [
        -43.71984100341797,
        3.4338607788085938
      ],
      [
        -2.2099437713623047,
        8.758827209472656
      ],
      [
        19.77365493774414,
        16.744583129882812
      ],
      [
        16.092578887939453,
        -0.43354034423828125
      ],
      [
        7.113063812255859,
        -16.94623565673828
      ],
      [
        2.9505233764648438,
        -11.557498931884766
      ]
    ],
    "explained_variance": [
      0.6209170818328857,
      0.1867847740650177,
      0.1064375787973404,
      0.06316855549812317,
      0.02269199676811695
    ]
  },
  "layer_22": {
    "experiment_name": "hsv_colour_one_red",
    "model_config": "Gemma-2-9B",
    "display_labels": [
      "Red",
      "Yellow",
      "Green",
      "Cyan",
      "Blue",
      "Magenta"
    ],
    "states_pca": [
      [
        -42.465576171875,
        5.231487274169922
      ],
      [
        -1.3613319396972656,
        8.437322616577148
      ],
      [
        21.94918441772461,
        15.488290786743164
      ],
      [
        16.288368225097656,
        -1.0889244079589844
      ],
      [
        4.581874847412109,
        -16.868927001953125
      ],
      [
        1.0075416564941406,
        -11.199207305908203
      ]
    ],
    "explained_variance": [
      0.6192216277122498,
      0.18031388521194458,
      0.11254305392503738,
      0.06471691280603409,
      0.023204496130347252
    ]
  },
  "layer_23": {
    "experiment_name": "hsv_colour_one_red",
    "model_config": "Gemma-2-9B",
    "display_labels": [
      "Red",
      "Yellow",
      "Green",
      "Cyan",
      "Blue",
      "Magenta"
    ],
    "states_pca": [
      [
        -41.071441650390625,
        6.721515655517578
      ],
      [
        -0.9686508178710938,
        6.325550079345703
      ],
      [
        22.54062271118164,
        16.14052391052246
      ],
      [
        16.032445907592773,
        -1.2482872009277344
      ],
      [
        3.359050750732422,
        -18.024227142333984
      ],
      [
        0.10790634155273438,
        -9.9150390625
      ]
    ],
    "explained_variance": [
      0.6035487651824951,
      0.18870192766189575,
      0.11787372827529907,
      0.0670861303806305,
      0.022789452224969864
    ]
  },
  "layer_24": {
    "experiment_name": "hsv_colour_one_red",
    "model_config": "Gemma-2-9B",
    "display_labels": [
      "Red",
      "Yellow",
      "Green",
      "Cyan",
      "Blue",
      "Magenta"
    ],
    "states_pca": [
      [
        -42.90696334838867,
        7.949678421020508
      ],
      [
        -0.19314193725585938,
        5.876258850097656
      ],
      [
        23.536544799804688,
        16.89152717590332
      ],
      [
        17.427135467529297,
        -0.5770111083984375
      ],
      [
        3.2730140686035156,
        -18.037372589111328
      ],
      [
        -1.1365699768066406,
        -12.103015899658203
      ]
    ],
    "explained_variance": [
      0.606085479259491,
      0.19121575355529785,
      0.11877594888210297,
      0.060631465166807175,
      0.023291343823075294
    ]
  },
  "layer_25": {
    "experiment_name": "hsv_colour_one_red",
    "model_config": "Gemma-2-9B",
    "display_labels": [
      "Red",
      "Yellow",
      "Green",
      "Cyan",
      "Blue",
      "Magenta"
    ],
    "states_pca": [
      [
        -41.78954315185547,
        9.59756088256836
      ],
      [
        1.319580078125,
        3.835611343383789
      ],
      [
        24.70813751220703,
        15.718668937683105
      ],
      [
        16.671977996826172,
        0.12427711486816406
      ],
      [
        1.082000732421875,
        -17.16191864013672
      ],
      [
        -1.9922256469726562,
        -12.114185333251953
      ]
    ],
    "explained_variance": [
      0.6160334348678589,
      0.1854386180639267,
      0.11611390858888626,
      0.060207296162843704,
      0.022206781432032585
    ]
  },
  "layer_26": {
    "experiment_name": "hsv_colour_one_red",
    "model_config": "Gemma-2-9B",
    "display_labels": [
      "Red",
      "Yellow",
      "Green",
      "Cyan",
      "Blue",
      "Magenta"
    ],
    "states_pca": [
      [
        -41.58573913574219,
        10.570473670959473
      ],
      [
        1.0740585327148438,
        3.932309150695801
      ],
      [
        26.35149383544922,
        15.08763313293457
      ],
      [
        17.479904174804688,
        -0.23865890502929688
      ],
      [
        -0.19333648681640625,
        -16.98468780517578
      ],
      [
        -3.12640380859375,
        -12.36713981628418
      ]
    ],
    "explained_variance": [
      0.6244606375694275,
      0.18146565556526184,
      0.11521320790052414,
      0.05730615183711052,
      0.021554363891482353
    ]
  },
  "layer_27": {
    "experiment_name": "hsv_colour_one_red",
    "model_config": "Gemma-2-9B",
    "display_labels": [
      "Red",
      "Yellow",
      "Green",
      "Cyan",
      "Blue",
      "Magenta"
    ],
    "states_pca": [
      [
        -42.967098236083984,
        11.031454086303711
      ],
      [
        1.4260025024414062,
        4.541158676147461
      ],
      [
        27.975940704345703,
        15.05729866027832
      ],
      [
        18.344436645507812,
        -0.8520355224609375
      ],
      [
        -0.6487159729003906,
        -17.548219680786133
      ],
      [
        -4.130817413330078,
        -12.229642868041992
      ]
    ],
    "explained_variance": [
      0.6313398480415344,
      0.17497850954532623,
      0.11774896085262299,
      0.05442323908209801,
      0.02150941640138626
    ]
  },
  "layer_28": {
    "experiment_name": "hsv_colour_one_red",
    "model_config": "Gemma-2-9B",
    "display_labels": [
      "Red",
      "Yellow",
      "Green",
      "Cyan",
      "Blue",
      "Magenta"
    ],
    "states_pca": [
      [
        -39.13550567626953,
        -10.201156616210938
      ],
      [
        1.6112632751464844,
        -6.566600799560547
      ],
      [
        26.13237762451172,
        -13.188465118408203
      ],
      [
        17.13770866394043,
        1.8249168395996094
      ],
      [
        -1.4413070678710938,
        16.00155258178711
      ],
      [
        -4.304542541503906,
        12.129684448242188
      ]
    ],
    "explained_variance": [
      0.6191738843917847,
      0.17797651886940002,
      0.12606945633888245,
      0.05488439276814461,
      0.021895715966820717
    ]
  },
  "layer_29": {
    "experiment_name": "hsv_colour_one_red",
    "model_config": "Gemma-2-9B",
    "display_labels": [
      "Red",
      "Yellow",
      "Green",
      "Cyan",
      "Blue",
      "Magenta"
    ],
    "states_pca": [
      [
        -40.13010787963867,
        11.327727317810059
      ],
      [
        2.1538429260253906,
        5.950256824493408
      ],
      [
        28.755788803100586,
        13.051589012145996
      ],
      [
        18.02907943725586,
        -2.6876440048217773
      ],
      [
        -2.998363494873047,
        -16.24985122680664
      ],
      [
        -5.810214996337891,
        -11.392078399658203
      ]
    ],
    "explained_variance": [
      0.6350640058517456,
      0.16615435481071472,
      0.12649518251419067,
      0.05110595002770424,
      0.021180521696805954
    ]
  },
  "layer_3": {
    "experiment_name": "hsv_colour_one_red",
    "model_config": "Gemma-2-9B",
    "display_labels": [
      "Red",
      "Yellow",
      "Green",
      "Cyan",
      "Blue",
      "Magenta"
    ],
    "states_pca": [
      [
        -2.2598876953125,
        0.13845854997634888
      ],
      [
        -0.30703163146972656,
        0.05191516876220703
      ],
      [
        0.46697425842285156,
        -0.1612028181552887
      ],
      [
        0.9511528015136719,
        1.0931874513626099
      ],
      [
        0.6142797470092773,
        -0.4482514262199402
      ],
      [
        0.534510612487793,
        -0.6741046905517578
      ]
    ],
    "explained_variance": [
      0.674765944480896,
      0.18331892788410187,
      0.09125495702028275,
      0.032733604311943054,
      0.017926543951034546
    ]
  },
  "layer_30": {
    "experiment_name": "hsv_colour_one_red",
    "model_config": "Gemma-2-9B",
    "display_labels": [
      "Red",
      "Yellow",
      "Green",
      "Cyan",
      "Blue",
      "Magenta"
    ],
    "states_pca": [
      [
        -41.015419006347656,
        11.137075424194336
      ],
      [
        1.7452201843261719,
        8.997335433959961
      ],
      [
        30.275096893310547,
        13.044893264770508
      ],
      [
        19.353063583374023,
        -4.768829345703125
      ],
      [
        -3.5999832153320312,
        -16.957233428955078
      ],
      [
        -6.757900238037109,
        -11.453254699707031
      ]
    ],
    "explained_variance": [
      0.6238077282905579,
      0.16784340143203735,
      0.1359759122133255,
      0.05209488794207573,
      0.02027806267142296
    ]
  },
  "layer_31": {
    "experiment_name": "hsv_colour_one_red",
    "model_config": "Gemma-2-9B",
    "display_labels": [
      "Red",
      "Yellow",
      "Green",
      "Cyan",
      "Blue",
      "Magenta"
    ],
    "states_pca": [
      [
        -44.24662780761719,
        7.132155418395996
      ],
      [
        0.41471099853515625,
        16.967588424682617
      ],
      [
        32.375160217285156,
        10.829209327697754
      ],
      [
        21.558738708496094,
        -7.888031005859375
      ],
      [
        -3.1087703704833984,
        -15.731042861938477
      ],
      [
        -6.993124008178711,
        -11.309877395629883
      ]
    ],
    "explained_variance": [
      0.6396187543869019,
      0.16194888949394226,
      0.1343892514705658,
      0.04538792744278908,
      0.018655212596058846
    ]
  },
  "layer_32": {
    "experiment_name": "hsv_colour_one_red",
    "model_config": "Gemma-2-9B",
    "display_labels": [
      "Red",
      "Yellow",
      "Green",
      "Cyan",
      "Blue",
      "Magenta"
    ],
    "states_pca": [
      [
        -46.56385803222656,
        6.780124664306641
      ],
      [
        1.533193588256836,
        18.953310012817383
      ],
      [
        34.255592346191406,
        10.103776931762695
      ],
      [
        22.366588592529297,
        -9.100408554077148
      ],
      [
        -3.400981903076172,
        -15.639047622680664
      ],
      [
        -8.190462112426758,
        -11.09775161743164
      ]
    ],
    "explained_variance": [
      0.6496294736862183,
      0.1586177945137024,
      0.13082334399223328,
      0.043704189360141754,
      0.01722523383796215
    ]
  },
  "layer_33": {
    "experiment_name": "hsv_colour_one_red",
    "model_config": "Gemma-2-9B",
    "display_labels": [
      "Red",
      "Yellow",
      "Green",
      "Cyan",
      "Blue",
      "Magenta"
    ],
    "states_pca": [
      [
        -48.3079719543457,
        5.199248313903809
      ],
      [
        1.844583511352539,
        21.511878967285156
      ],
      [
        35.96419906616211,
        8.31640911102295
      ],
      [
        23.4207820892334,
        -10.187610626220703
      ],
      [
        -3.913832187652588,
        -14.283095359802246
      ],
      [
        -9.007715225219727,
        -10.5568208694458
      ]
    ],
    "explained_variance": [
      0.6612885594367981,
      0.15129750967025757,
      0.12930236756801605,
      0.04171641916036606,
      0.016395052894949913
    ]
  },
  "layer_34": {
    "experiment_name": "hsv_colour_one_red",
    "model_config": "Gemma-2-9B",
    "display_labels": [
      "Red",
      "Yellow",
      "Green",
      "Cyan",
      "Blue",
      "Magenta"
    ],
    "states_pca": [
      [
        -51.57952117919922,
        -3.2371749877929688
      ],
      [
        2.0981826782226562,
        -24.937965393066406
      ],
      [
        38.4322509765625,
        -6.835659027099609
      ],
      [
        25.835432052612305,
        11.82790756225586
      ],
      [
        -4.122864723205566,
        13.713478088378906
      ],
      [
        -10.663445472717285,
        9.469482421875
      ]
    ],
    "explained_variance": [
      0.6700894832611084,
      0.14876580238342285,
      0.12406499683856964,
      0.04148021712899208,
      0.015599505975842476
    ]
  },
  "layer_35": {
    "experiment_name": "hsv_colour_one_red",
    "model_config": "Gemma-2-9B",
    "display_labels": [
      "Red",
      "Yellow",
      "Green",
      "Cyan",
      "Blue",
      "Magenta"
    ],
    "states_pca": [
      [
        -52.6397705078125,
        -3.1236953735351562
      ],
      [
        1.8475008010864258,
        -26.171844482421875
      ],
      [
        40.148963928222656,
        -6.544517517089844
      ],
      [
        26.882408142089844,
        12.1734619140625
      ],
      [
        -4.810833930969238,
        13.584220886230469
      ],
      [
        -11.428252220153809,
        10.082357406616211
      ]
    ],
    "explained_variance": [
      0.6684411764144897,
      0.14885246753692627,
      0.1253107637166977,
      0.041836634278297424,
      0.015558989718556404
    ]
  },
  "layer_36": {
    "experiment_name": "hsv_colour_one_red",
    "model_config": "Gemma-2-9B",
    "display_labels": [
      "Red",
      "Yellow",
      "Green",
      "Cyan",
      "Blue",
      "Magenta"
    ],
    "states_pca": [
      [
        -54.870704650878906,
        -4.542259216308594
      ],
      [
        3.5115585327148438,
        -25.89996910095215
      ],
      [
        41.24810028076172,
        -7.08660888671875
      ],
      [
        27.36511993408203,
        12.378546714782715
      ],
      [
        -4.960529327392578,
        14.246434211730957
      ],
      [
        -12.293571472167969,
        10.90395450592041
      ]
    ],
    "explained_variance": [
      0.6770725250244141,
      0.1458326280117035,
      0.12042075395584106,
      0.04167023301124573,
      0.015003863722085953
    ]
  },
  "layer_37": {
    "experiment_name": "hsv_colour_one_red",
    "model_config": "Gemma-2-9B",
    "display_labels": [
      "Red",
      "Yellow",
      "Green",
      "Cyan",
      "Blue",
      "Magenta"
    ],
    "states_pca": [
      [
        -59.13859558105469,
        -5.71668815612793
      ],
      [
        3.6887741088867188,
        -26.778404235839844
      ],
      [
        44.941375732421875,
        -8.34135627746582
      ],
      [
        29.63439178466797,
        13.064407348632812
      ],
      [
        -5.6746063232421875,
        15.686417579650879
      ],
      [
        -13.451305389404297,
        12.085630416870117
      ]
    ],
    "explained_variance": [
      0.68405681848526,
      0.14277561008930206,
      0.11826121807098389,
      0.04001766815781593,
      0.014888687990605831
    ]
  },
  "layer_38": {
    "experiment_name": "hsv_colour_one_red",
    "model_config": "Gemma-2-9B",
    "display_labels": [
      "Red",
      "Yellow",
      "Green",
      "Cyan",
      "Blue",
      "Magenta"
    ],
    "states_pca": [
      [
        -62.572479248046875,
        9.82004165649414
      ],
      [
        4.9740753173828125,
        26.472599029541016
      ],
      [
        48.528236389160156,
        11.402236938476562
      ],
      [
        31.037181854248047,
        -13.700336456298828
      ],
      [
        -6.816903114318848,
        -19.24162483215332
      ],
      [
        -15.150069236755371,
        -14.752876281738281
      ]
    ],
    "explained_variance": [
      0.6744315028190613,
      0.15242773294448853,
      0.11866786330938339,
      0.039606135338544846,
      0.014866826124489307
    ]
  },
  "layer_39": {
    "experiment_name": "hsv_colour_one_red",
    "model_config": "Gemma-2-9B",
    "display_labels": [
      "Red",
      "Yellow",
      "Green",
      "Cyan",
      "Blue",
      "Magenta"
    ],
    "states_pca": [
      [
        -69.74678802490234,
        -10.700786590576172
      ],
      [
        6.257568359375,
        -29.895606994628906
      ],
      [
        53.55449676513672,
        -12.242073059082031
      ],
      [
        34.602638244628906,
        15.537604331970215
      ],
      [
        -7.7226104736328125,
        20.6856746673584
      ],
      [
        -16.945388793945312,
        16.615158081054688
      ]
    ],
    "explained_variance": [
      0.6765881776809692,
      0.15276993811130524,
      0.11969595402479172,
      0.03721434995532036,
      0.013731522485613823
    ]
  },
  "layer_4": {
    "experiment_name": "hsv_colour_one_red",
    "model_config": "Gemma-2-9B",
    "display_labels": [
      "Red",
      "Yellow",
      "Green",
      "Cyan",
      "Blue",
      "Magenta"
    ],
    "states_pca": [
      [
        -2.641551971435547,
        -0.12997102737426758
      ],
      [
        -0.27641868591308594,
        0.14408016204833984
      ],
      [
        0.5512847900390625,
        -0.1095128059387207
      ],
      [
        0.9822559356689453,
        -1.080578327178955
      ],
      [
        0.6825332641601562,
        0.3690671920776367
      ],
      [
        0.7019100189208984,
        0.8069090843200684
      ]
    ],
    "explained_variance": [
      0.6741741299629211,
      0.14560775458812714,
      0.08786138892173767,
      0.058231767266988754,
      0.034125037491321564
    ]
  },
  "layer_40": {
    "experiment_name": "hsv_colour_one_red",
    "model_config": "Gemma-2-9B",
    "display_labels": [
      "Red",
      "Yellow",
      "Green",
      "Cyan",
      "Blue",
      "Magenta"
    ],
    "states_pca": [
      [
        -78.3283920288086,
        14.27094554901123
      ],
      [
        6.276023864746094,
        31.167213439941406
      ],
      [
        61.82770538330078,
        15.192294120788574
      ],
      [
        39.817222595214844,
        -16.29262924194336
      ],
      [
        -9.698150634765625,
        -24.561939239501953
      ],
      [
        -19.89441680908203,
        -19.77585792541504
      ]
    ],
    "explained_variance": [
      0.677516758441925,
      0.14959806203842163,
      0.11781947314739227,
      0.03987957909703255,
      0.015186072327196598
    ]
  },
  "layer_41": {
    "experiment_name": "hsv_colour_one_red",
    "model_config": "Gemma-2-9B",
    "display_labels": [
      "Red",
      "Yellow",
      "Green",
      "Cyan",
      "Blue",
      "Magenta"
    ],
    "states_pca": [
      [
        -84.06407928466797,
        -15.579519271850586
      ],
      [
        7.7895965576171875,
        -36.52458190917969
      ],
      [
        66.14688110351562,
        -16.16293716430664
      ],
      [
        41.9945068359375,
        18.934741973876953
      ],
      [
        -9.885246276855469,
        27.546066284179688
      ],
      [
        -21.981590270996094,
        21.78626251220703
      ]
    ],
    "explained_variance": [
      0.6549602150917053,
      0.16223250329494476,
      0.12374740839004517,
      0.04208473488688469,
      0.016975095495581627
    ]
  },
  "layer_42": {
    "experiment_name": "hsv_colour_one_red",
    "model_config": "Gemma-2-9B",
    "display_labels": [
      "Red",
      "Yellow",
      "Green",
      "Cyan",
      "Blue",
      "Magenta"
    ],
    "states_pca": [
      [
        29.491973876953125,
        -8.148796081542969
      ],
      [
        -3.156704902648926,
        -11.196020126342773
      ],
      [
        -25.238237380981445,
        -6.877929210662842
      ],
      [
        -14.830238342285156,
        6.530475616455078
      ],
      [
        4.682732105255127,
        11.443241119384766
      ],
      [
        9.050474166870117,
        8.249034881591797
      ]
    ],
    "explained_variance": [
      0.6480675339698792,
      0.16926337778568268,
      0.12303710728883743,
      0.04309165105223656,
      0.016540326178073883
    ]
  },
  "layer_5": {
    "experiment_name": "hsv_colour_one_red",
    "model_config": "Gemma-2-9B",
    "display_labels": [
      "Red",
      "Yellow",
      "Green",
      "Cyan",
      "Blue",
      "Magenta"
    ],
    "states_pca": [
      [
        -5.871152877807617,
        -0.0022115707397460938
      ],
      [
        0.8312568664550781,
        1.3780994415283203
      ],
      [
        1.104013204574585,
        -1.377446174621582
      ],
      [
        1.2535088062286377,
        -1.6091136932373047
      ],
      [
        1.1995530128479004,
        0.03220653533935547
      ],
      [
        1.4828269481658936,
        1.5784626007080078
      ]
    ],
    "explained_variance": [
      0.6873940825462341,
      0.14674276113510132,
      0.08817929029464722,
      0.04925501346588135,
      0.0284288227558136
    ]
  },
  "layer_6": {
    "experiment_name": "hsv_colour_one_red",
    "model_config": "Gemma-2-9B",
    "display_labels": [
      "Red",
      "Yellow",
      "Green",
      "Cyan",
      "Blue",
      "Magenta"
    ],
    "states_pca": [
      [
        7.290524482727051,
        0.11133575439453125
      ],
      [
        -1.0724010467529297,
        1.2887439727783203
      ],
      [
        -1.3294563293457031,
        -1.4430809020996094
      ],
      [
        -1.2537765502929688,
        -1.6840801239013672
      ],
      [
        -1.6401748657226562,
        -0.040935516357421875
      ],
      [
        -1.9947128295898438,
        1.7680397033691406
      ]
    ],
    "explained_variance": [
      0.7426345944404602,
      0.1122375950217247,
      0.07702358067035675,
      0.0437992587685585,
      0.02430499903857708
    ]
  },
  "layer_7": {
    "experiment_name": "hsv_colour_one_red",
    "model_config": "Gemma-2-9B",
    "display_labels": [
      "Red",
      "Yellow",
      "Green",
      "Cyan",
      "Blue",
      "Magenta"
    ],
    "states_pca": [
      [
        12.308347702026367,
        -0.2986459732055664
      ],
      [
        -0.980433464050293,
        1.98884916305542
      ],
      [
        -2.7765674591064453,
        1.4356532096862793
      ],
      [
        -2.4184627532958984,
        1.0361876487731934
      ],
      [
        -3.2731552124023438,
        -0.5217781066894531
      ],
      [
        -2.8597278594970703,
        -3.640256881713867
      ]
    ],
    "explained_variance": [
      0.7660450339317322,
      0.08577084541320801,
      0.07968282699584961,
      0.045942384749650955,
      0.02255893684923649
    ]
  },
  "layer_8": {
    "experiment_name": "hsv_colour_one_red",
    "model_config": "Gemma-2-9B",
    "display_labels": [
      "Red",
      "Yellow",
      "Green",
      "Cyan",
      "Blue",
      "Magenta"
    ],
    "states_pca": [
      [
        14.184818267822266,
        -0.05167579650878906
      ],
      [
        -0.6884326934814453,
        0.6493778228759766
      ],
      [
        -3.193035125732422,
        1.9406318664550781
      ],
      [
        -2.904132843017578,
        0.9746532440185547
      ],
      [
        -4.190776824951172,
        1.0835742950439453
      ],
      [
        -3.2084827423095703,
        -4.596591949462891
      ]
    ],
    "explained_variance": [
      0.7930240035057068,
      0.08769448846578598,
      0.06587129831314087,
      0.036264918744564056,
      0.017145328223705292
    ]
  },
  "layer_9": {
    "experiment_name": "hsv_colour_one_red",
    "model_config": "Gemma-2-9B",
    "display_labels": [
      "Red",
      "Yellow",
      "Green",
      "Cyan",
      "Blue",
      "Magenta"
    ],
    "states_pca": [
      [
        17.815963745117188,
        -0.3443880081176758
      ],
      [
        -1.1809329986572266,
        -0.06356048583984375
      ],
      [
        -4.134637832641602,
        -1.7834243774414062
      ],
      [
        -3.6869258880615234,
        -1.9178740978240967
      ],
      [
        -5.554294586181641,
        -2.182227611541748
      ],
      [
        -3.2591724395751953,
        6.291484355926514
      ]
    ],
    "explained_variance": [
      0.7553123235702515,
      0.09915842115879059,
      0.07986310869455338,
      0.04287802055478096,
      0.02278810553252697
    ]
  }
}